exray/__init__.py
exray/main.py
exray-0.0.1.dist-info/licenses/LICENSE
exray-0.0.1.dist-info/METADATA
exray-0.0.1.dist-info/WHEEL
exray-0.0.1.dist-info/top_level.txt
exray-0.0.1.dist-info/RECORD
