Metadata-Version: 2.4
Name: exray
Version: 0.0.1
Summary: Unified Control Plane for distributed computing
Requires-Python: >=3.12
License-File: LICENSE
Requires-Dist: dearpygui>=2.1.0
Dynamic: license-file
